{"assets/co2.png":["assets/co2.png"],"assets/escudo_62_anios.png":["assets/escudo_62_anios.png"],"assets/escudounipamplona.png":["assets/escudounipamplona.png"],"assets/escudounipamplona_redux.png":["assets/escudounipamplona_redux.png"],"assets/hum.png":["assets/hum.png"],"assets/invernadero.png":["assets/invernadero.png"],"assets/invernadero1.png":["assets/invernadero1.png"],"assets/invernadero1_1.jpg":["assets/invernadero1_1.jpg"],"assets/invernadero1_2.jpg":["assets/invernadero1_2.jpg"],"assets/invernadero1_3.jpg":["assets/invernadero1_3.jpg"],"assets/invernadero2.png":["assets/invernadero2.png"],"assets/invernadero2_1.jpg":["assets/invernadero2_1.jpg"],"assets/invernadero2_2.jpg":["assets/invernadero2_2.jpg"],"assets/invernadero2_3.jpg":["assets/invernadero2_3.jpg"],"assets/invernadero3_1.jpg":["assets/invernadero3_1.jpg"],"assets/invernadero3_2.jpg":["assets/invernadero3_2.jpg"],"assets/invernadero3_3.jpg":["assets/invernadero3_3.jpg"],"assets/invernadero_real.jpg":["assets/invernadero_real.jpg"],"assets/logo_acreditacion.png":["assets/logo_acreditacion.png"],"assets/slogan_negro.png":["assets/slogan_negro.png"],"assets/slogan_negro_redux.png":["assets/slogan_negro_redux.png"],"assets/temp.png":["assets/temp.png"],"packages/cupertino_icons/assets/CupertinoIcons.ttf":["packages/cupertino_icons/assets/CupertinoIcons.ttf"]}